socrates_gui/__init__.py
socrates_gui/package.json
socrates_gui/settings.py
socrates_gui/tests.py
socrates_gui/urls.py
socrates_gui/views.py
socrates_gui/websocket.py
socrates_gui/static/css/main.241a8c12.css
socrates_gui/static/css/main.241a8c12.css.map
socrates_gui/static/css/spice.css
socrates_gui/static/js/app.spice-html5.browserify.js
socrates_gui/static/js/main.2e79e998.js
socrates_gui/static/js/main.2e79e998.js.map
socrates_gui/static/js/spice-html5.js
socrates_gui/static/media/glyphicons-halflings-regular.448c34a5.woff2
socrates_gui/static/media/glyphicons-halflings-regular.89889688.svg
socrates_gui/static/media/glyphicons-halflings-regular.e18bbf61.ttf
socrates_gui/static/media/glyphicons-halflings-regular.f4769f9b.eot
socrates_gui/static/media/glyphicons-halflings-regular.fa277232.woff
socrates_gui/templates/asset_console.jnlp
socrates_gui/templates/asset_console_spice.html
socrates_gui/templates/index.html
socrates_gui-2.1.2.dist-info/AUTHORS.txt
socrates_gui-2.1.2.dist-info/LICENSE.txt
socrates_gui-2.1.2.dist-info/METADATA
socrates_gui-2.1.2.dist-info/WHEEL
socrates_gui-2.1.2.dist-info/top_level.txt
socrates_gui-2.1.2.dist-info/RECORD
