Metadata-Version: 2.1
Name: socrates-gui
Version: 2.1.2
Summary: Source of Truth for hardware, virtual machines, and networks
Home-page: https://github.com/dhozac/socrates_gui
Author: Klarna Bank AB
Author-email: daniel.zakrisson@klarna.com
License: Apache Software License
Platform: UNKNOWN
Classifier: Development Status :: 7 - Inactive
Classifier: Environment :: Web Environment
Classifier: Framework :: Django :: 1.11
Classifier: Intended Audience :: System Administrators
Classifier: License :: OSI Approved :: Apache Software License
Classifier: Topic :: System :: Installation/Setup
Requires-Dist: websockify
Requires-Dist: socrates-api
